MANIFEST.in
README.md
setup.cfg
setup.py
engraver.egg-info/PKG-INFO
engraver.egg-info/SOURCES.txt
engraver.egg-info/dependency_links.txt
engraver.egg-info/entry_points.txt
engraver.egg-info/pbr.json
engraver.egg-info/requires.txt
engraver.egg-info/top_level.txt
src/__init__.py
src/ansible.py
src/args.json
src/aws.py
src/cluster_command.py
src/colors.py
src/configure_command.py
src/deploy_command.py
src/engraver.py
src/init_command.py
src/job_command.py
src/logs_command.py
src/machines_command.py
src/service_command.py
src/util.py
src/ansible_template/ansible.cfg
src/ansible_template/cluster_remove.yml
src/ansible_template/deploy.yml
src/ansible_template/engraver_aws.yml
src/ansible_template/engraver_post.yml
src/ansible_template/job_kill.yml
src/ansible_template/job_submit.yml
src/ansible_template/machines_remove.yml
src/ansible_template/refresh_cache.yml
src/ansible_template/group_vars/all.yml
src/ansible_template/vars/cluster_vars/machine_profiles/default_profile.yml
src/ansible_template/vars/cluster_vars/machine_profiles/profile_template.yml