Metadata-Version: 1.0
Name: engraver
Version: 0.1.5
Summary: A tool for cutting Onyx
Home-page: https://github.com/onyx-platform/engraver
Author: Distributed Masonry
Author-email: support@onyxplatform.org
License: Eclipse
Platform: UNKNOWN
